Uniq_input(10)/uniq.v
// Реализовать модуль, который выводит на экран 4 последних уникальных значения из входного потока данных.
// Значения на выходе должны быть отсортированы по времени, прошедшему с момента их получения. 
// Активные выходы должны быть отмечены сигналом валидности.

module uniq(
    input clk,
    input signed [7:0] data_in,
    input data_en,

    output reg signed [7:0] out_1,
    output reg signed [7:0] out_2,
    output reg signed [7:0] out_3,  
    output reg signed [7:0] out_4,

    output reg val_1,
    output reg val_2,
    output reg val_3,
    output reg val_4
    );

    reg found = 0;

    initial begin
        val_1 = 0;
        val_2 = 0;
        val_3 = 0;
        val_4 = 0;
        out_1 = 0;
        out_2 = 0;
        out_3 = 0;
        out_4 = 0;
    end

    always @(posedge clk) begin
        if (data_en) begin
            found = 0;

            // Проверяем, есть ли входное значение уже среди выходов
            if (data_in == out_1) begin
                found = 1;
            end else if (data_in == out_2) begin
                found = 1;
                out_2 = out_1;
            end else if (data_in == out_3) begin
                found = 1;
                out_3 = out_2;
                out_2 = out_1;
            end else if (data_in == out_4) begin
                found = 1;
                out_4 = out_3;
                out_3 = out_2;
                out_2 = out_1;
            end

            // Если значение найдено, обновляем его позицию
            if (found) begin
                out_1 = data_in;
            end else begin
            // Сдвигаем все значения вправо и вставляем новое значение в out_1
                out_4 = out_3;
                out_3 = out_2;
                out_2 = out_1;
                out_1 = data_in;
            end

            // Обновляем сигналы валидности
            val_1 = (out_1 != 0) ? 1 : 0;
            val_2 = (out_2 != 0) ? 1 : 0;
            val_3 = (out_3 != 0) ? 1 : 0;
            val_4 = (out_4 != 0) ? 1 : 0;
        end
    end

endmodule

Uniq_input(10)/tb_uniq.v
`timescale 1ns / 1ns

module tb_uniq;

    reg clk = 0;
    reg data_en = 0;
    reg signed [7:0] data_in = 0;

    wire signed [7:0] out_1;
    wire signed [7:0] out_2;
    wire signed [7:0] out_3;
    wire signed [7:0] out_4;
    wire val_1;
    wire val_2;
    wire val_3;
    wire val_4;

    // Тактовый сигнал
    initial begin
        forever #5 clk = ~clk;
    end

    initial begin

        #10
        data_en <= 1;
        data_in <= 1;

        #10
        data_in <= 2;       #10
        data_in <= 1;       #10
        data_in <= 2;       #10
        data_in <= 3;       #10
        data_in <= 4;       #10
        data_in <= 3;       #10
        data_in <= 2;       #10
        data_in <= 3;       #10
        data_in <= 4;       #10
        data_in <= 3;       #10
        data_in <= 4;       #10
        data_in <= 1;       #10
        data_in <= 2;       #10

        data_en <= 0;

        #100
        $finish;
    end

    uniq dut (
        .clk(clk),
        .data_in(data_in),
        .data_en(data_en),
        .out_1(out_1),
        .out_2(out_2),
        .out_3(out_3),
        .out_4(out_4),
        .val_1(val_1),
        .val_2(val_2),
        .val_3(val_3),
        .val_4(val_4)
    );

    initial
    begin
        $dumpfile("test.vcd");
        $dumpvars;
    end

endmodule

Uniq_input(10)/test.vcd
$date
	Thu Jun  6 01:11:59 2024
$end
$version
	Icarus Verilog
$end
$timescale
	1ns
$end
$scope module tb_uniq $end
$var wire 1 ! val_4 $end
$var wire 1 " val_3 $end
$var wire 1 # val_2 $end
$var wire 1 $ val_1 $end
$var wire 8 % out_4 [7:0] $end
$var wire 8 & out_3 [7:0] $end
$var wire 8 ' out_2 [7:0] $end
$var wire 8 ( out_1 [7:0] $end
$var reg 1 ) clk $end
$var reg 1 * data_en $end
$var reg 8 + data_in [7:0] $end
$scope module dut $end
$var wire 1 ) clk $end
$var wire 1 * data_en $end
$var wire 8 , data_in [7:0] $end
$var reg 1 - found $end
$var reg 8 . out_1 [7:0] $end
$var reg 8 / out_2 [7:0] $end
$var reg 8 0 out_3 [7:0] $end
$var reg 8 1 out_4 [7:0] $end
$var reg 1 $ val_1 $end
$var reg 1 # val_2 $end
$var reg 1 " val_3 $end
$var reg 1 ! val_4 $end
$upscope $end
$upscope $end
$enddefinitions $end
#0
$dumpvars
b0 1
b0 0
b0 /
b0 .
0-
b0 ,
b0 +
0*
0)
b0 (
b0 '
b0 &
b0 %
0$
0#
0"
0!
$end
#5
1)
#10
b1 +
b1 ,
1*
0)
#15
1$
b1 (
b1 .
1)
#20
b10 +
b10 ,
0)
#25
1#
b10 (
b10 .
b1 '
b1 /
1)
#30
b1 +
b1 ,
0)
#35
b1 (
b1 .
b10 '
b10 /
1-
1)
#40
b10 +
b10 ,
0)
#45
b10 (
b10 .
b1 '
b1 /
1-
1)
#50
b11 +
b11 ,
0)
#55
1"
b11 (
b11 .
b10 '
b10 /
b1 &
b1 0
0-
1)
#60
b100 +
b100 ,
0)
#65
1!
b100 (
b100 .
b11 '
b11 /
b10 &
b10 0
b1 %
b1 1
1)
#70
b11 +
b11 ,
0)
#75
b11 (
b11 .
b100 '
b100 /
1-
1)
#80
b10 +
b10 ,
0)
#85
b10 (
b10 .
b11 '
b11 /
b100 &
b100 0
1-
1)
#90
b11 +
b11 ,
0)
#95
b11 (
b11 .
b10 '
b10 /
1-
1)
#100
b100 +
b100 ,
0)
#105
b100 (
b100 .
b11 '
b11 /
b10 &
b10 0
1-
1)
#110
b11 +
b11 ,
0)
#115
b11 (
b11 .
b100 '
b100 /
1-
1)
#120
b100 +
b100 ,
0)
#125
b100 (
b100 .
b11 '
b11 /
1-
1)
#130
b1 +
b1 ,
0)
#135
b1 (
b1 .
b100 '
b100 /
b11 &
b11 0
b10 %
b10 1
1-
1)
#140
b10 +
b10 ,
0)
#145
b10 (
b10 .
b1 '
b1 /
b100 &
b100 0
b11 %
b11 1
1-
1)
#150
0*
0)
